intensipy/__init__.py
intensipy/models.py
intensipy-0.1.0.dist-info/LICENSE
intensipy-0.1.0.dist-info/METADATA
intensipy-0.1.0.dist-info/WHEEL
intensipy-0.1.0.dist-info/top_level.txt
intensipy-0.1.0.dist-info/RECORD
