Metadata-Version: 2.1
Name: intensipy
Version: 0.1.0
Summary: Normalize intensity values in 3D images.
Home-page: https://github.com/dakota-hawkins/intensipy
Author: Dakota Y. Hawkins
Author-email: dyh0110@bu.edu
License: BSD
Platform: UNKNOWN
Classifier: Programming Language :: Python :: 3
Requires-Dist: numpy
Requires-Dist: scipy
Requires-Dist: scikit-image
Requires-Dist: statsmodels
